MANIFEST.in
REQUIREMENTS
distribute_setup.py
setup.py
src/django_boss.egg-info/PKG-INFO
src/django_boss.egg-info/SOURCES.txt
src/django_boss.egg-info/dependency_links.txt
src/django_boss.egg-info/entry_points.txt
src/django_boss.egg-info/requires.txt
src/django_boss.egg-info/top_level.txt
src/djboss/__init__.py
src/djboss/cli.py
src/djboss/commands.py
src/djboss/parser.py