Metadata-Version: 1.0
Name: django-boss
Version: 0.6.2
Summary: Django management commands, revisited.
Home-page: http://github.com/zacharyvoase/django-boss
Author: Zachary Voase
Author-email: zacharyvoase@me.com
License: UNKNOWN
Platform: UNKNOWN
